lattice_algebra/__init__.py
lattice_algebra/main.py
lattice_algebra-0.1.1.dist-info/LICENSE
lattice_algebra-0.1.1.dist-info/METADATA
lattice_algebra-0.1.1.dist-info/WHEEL
lattice_algebra-0.1.1.dist-info/top_level.txt
lattice_algebra-0.1.1.dist-info/RECORD
