Metadata-Version: 2.1
Name: lattice_algebra
Version: 0.1.1
Summary: Algebraic infrastructure for cryptographic schemes in lattice settings.
Home-page: https://github.com/geometry-labs/lattice-algebra
Author: Geometry Labs
Author-email: info@geometrylabs.io
License: MIT
Keywords: lattice,cryptography,crypto
Platform: UNKNOWN
Classifier: Development Status :: 5 - Production/Stable
Classifier: Environment :: Console
Classifier: Intended Audience :: Developers
Classifier: Natural Language :: English
Classifier: License :: OSI Approved :: BSD License
Classifier: Programming Language :: Python :: 3 :: Only
Classifier: Programming Language :: Python :: 3
Classifier: Programming Language :: Python :: 3.6
Classifier: Programming Language :: Python :: 3.7
Classifier: Programming Language :: Python :: 3.8
Classifier: Programming Language :: Python :: 3.9
Classifier: Programming Language :: Python :: 3.10
Classifier: Programming Language :: Python :: Implementation :: CPython
Classifier: Programming Language :: Python :: Implementation :: PyPy
Classifier: Programming Language :: Python
Classifier: Topic :: Software Development
Requires-Python: >=3.6
License-File: LICENSE
